veeml/__init__.py
veeml/models/__init__.py
veeml/models/decision_tree.py
veeml/models/knn.py
veeml/models/linear_regression.py
veeml/models/logistic_regression.py
veeml/models/multivariate_regression.py
veeml/models/random_forest.py
veeml/utils/__init__.py
veeml/utils/data_processing.py
veeml/utils/evaluation.py
veeml-0.1.0.dist-info/METADATA
veeml-0.1.0.dist-info/WHEEL
veeml-0.1.0.dist-info/entry_points.txt
veeml-0.1.0.dist-info/top_level.txt
veeml-0.1.0.dist-info/RECORD
