Metadata-Version: 2.2
Name: veeml
Version: 0.1.0
Summary: A package for machine learning models and utilities
Home-page: https://github.com/vishnupriya230604/vee.git
Author: Vishnupriya K
Author-email: vishnupriyakarthy@gmail.com
Classifier: Programming Language :: Python :: 3
Classifier: License :: OSI Approved :: MIT License
Classifier: Operating System :: OS Independent
Requires-Python: >=3.7
Requires-Dist: numpy>=1.21.0
Requires-Dist: scikit-learn>=1.0.0
Dynamic: author
Dynamic: author-email
Dynamic: classifier
Dynamic: description
Dynamic: description-content-type
Dynamic: home-page
Dynamic: requires-dist
Dynamic: requires-python
Dynamic: summary
